jeeves/__init__.py
jeeves/cli.py
jeeves/commands/__init__.py
jeeves/commands/find_packages.py
jeeves/commands/flakehell.py
jeeves/commands/format.py
jeeves/commands/isort.py
jeeves/commands/lint.py
jeeves/commands/mypy.py
jeeves/commands/subprocess.py
jeeves/py.typed
mister_jeeves-0.0.3.dist-info/entry_points.txt
mister_jeeves-0.0.3.dist-info/LICENSE
mister_jeeves-0.0.3.dist-info/WHEEL
mister_jeeves-0.0.3.dist-info/METADATA
mister_jeeves-0.0.3.dist-info/RECORD
