Metadata-Version: 2.1
Name: mister-jeeves
Version: 0.0.3
Summary: Mr Jeeves will be happy to help you managing your Python project sir.
Home-page: https://github.com/python-jeeves/jeeves
License: MIT
Requires-Python: >=3.6,<3.10
Classifier: Development Status :: 3 - Alpha
Classifier: Intended Audience :: Developers
Classifier: License :: OSI Approved :: MIT License
Classifier: Operating System :: OS Independent
Classifier: Programming Language :: Python :: 3
Classifier: Programming Language :: Python :: 3.6
Classifier: Programming Language :: Python :: 3.7
Classifier: Programming Language :: Python :: 3.8
Classifier: Topic :: Software Development :: Libraries :: Python Modules
Requires-Dist: dependencies (>=6.0.1,<7.0.0)
Requires-Dist: flakehell (>=0.9.0,<0.10.0)
Requires-Dist: isort (>=5.7.0,<6.0.0)
Requires-Dist: mypy (>=0.812,<0.813)
Requires-Dist: typer (>=0.3.2,<0.4.0)
Requires-Dist: wemake-python-styleguide (>=0.15.1,<0.16.0)
Project-URL: Repository, https://github.com/python-jeeves/jeeves
